appengine/__init__.py
appengine/main.py
appengine/server.py
appengine/handlers/__init__.py
appengine/handlers/base_handler.py
appengine/handlers/bots.py
appengine/handlers/commit_range.py
appengine/handlers/configuration.py
appengine/handlers/corpora.py
appengine/handlers/coverage_report.py
appengine/handlers/crash_query.py
appengine/handlers/crash_stats.py
appengine/handlers/domain_verifier.py
appengine/handlers/download.py
appengine/handlers/external_update.py
appengine/handlers/fuzzer_stats.py
appengine/handlers/fuzzers.py
appengine/handlers/gcs_redirector.py
appengine/handlers/help_redirector.py
appengine/handlers/home.py
appengine/handlers/issue_redirector.py
appengine/handlers/jobs.py
appengine/handlers/login.py
appengine/handlers/report_csp_failure.py
appengine/handlers/revisions_info.py
appengine/handlers/testcase_list.py
appengine/handlers/upload_testcase.py
appengine/handlers/viewer.py
appengine/handlers/cron/__init__.py
appengine/handlers/cron/backup.py
appengine/handlers/cron/batch_fuzzer_jobs.py
appengine/handlers/cron/build_crash_stats.py
appengine/handlers/cron/cleanup.py
appengine/handlers/cron/corpus_backup.py
appengine/handlers/cron/fuzz_strategy_selection.py
appengine/handlers/cron/fuzzer_and_job_weights.py
appengine/handlers/cron/fuzzer_coverage.py
appengine/handlers/cron/group_leader.py
appengine/handlers/cron/grouper.py
appengine/handlers/cron/load_bigquery_stats.py
appengine/handlers/cron/manage_vms.py
appengine/handlers/cron/ml_train.py
appengine/handlers/cron/oss_fuzz_apply_ccs.py
appengine/handlers/cron/oss_fuzz_build_status.py
appengine/handlers/cron/oss_fuzz_generate_certs.py
appengine/handlers/cron/predator_pull.py
appengine/handlers/cron/project_setup.py
appengine/handlers/cron/recurring_tasks.py
appengine/handlers/cron/schedule_corpus_pruning.py
appengine/handlers/cron/service_accounts.py
appengine/handlers/cron/sync_admins.py
appengine/handlers/cron/triage.py
appengine/handlers/cron/helpers/__init__.py
clusterfuzz-2.6.0.dist-info/METADATA
clusterfuzz-2.6.0.dist-info/WHEEL
clusterfuzz-2.6.0.dist-info/top_level.txt
clusterfuzz-2.6.0.dist-info/RECORD
